yasta/__init__.py
yasta/utils.py
yasta/yasta.py
yasta-0.1.3.dist-info/entry_points.txt
yasta-0.1.3.dist-info/LICENSE
yasta-0.1.3.dist-info/WHEEL
yasta-0.1.3.dist-info/METADATA
yasta-0.1.3.dist-info/RECORD
