Metadata-Version: 2.1
Name: yasta
Version: 0.1.3
Summary: A modern task runner.
Home-page: https://github.com/adhamsalama/yasta
License: MIT
Author: Adham Salama
Author-email: adhamsalama@zohomail.com
Requires-Python: >=3.10,<4.0
Classifier: License :: OSI Approved :: MIT License
Classifier: Programming Language :: Python :: 3
Classifier: Programming Language :: Python :: 3.10
Classifier: Programming Language :: Python :: 3.11
Requires-Dist: toml (>=0.10.2,<0.11.0)
Requires-Dist: typer[all] (>=0.6.1,<0.7.0)
Project-URL: Bug Tracker, https://github.com/adhamsalama/yasta/issues
Project-URL: Repository, https://github.com/adhamsalama/yasta
